<archimate:ArchimateDiagramModel
    xmlns:xsi="http://www.w3.org/2001/XMLSchema-instance"
    xmlns:archimate="http://www.archimatetool.com/archimate"
    name="Stakeholder Motivation"
    id="id-32fbe59404a4404fb3238c951441afb4">
  <children
      xsi:type="archimate:DiagramModelArchimateObject"
      id="id-49a64da01e20492981168eec69f34d51">
    <bounds
        x="168"
        y="48"
        width="505"
        height="73"/>
    <archimateElement
        xsi:type="archimate:Goal"
        href="Goal_id-0fc6a0644c5c46178fb14b91343e06e1.xml#id-0fc6a0644c5c46178fb14b91343e06e1"/>
  </children>
  <children
      xsi:type="archimate:DiagramModelArchimateObject"
      id="id-c5e6f4e5902f41ba9d06ab551553b97b">
    <bounds
        x="72"
        y="192"
        width="193"
        height="85"/>
    <archimateElement
        xsi:type="archimate:Stakeholder"
        href="Stakeholder_id-ce7a0d4d7dfa4c5aaf99fd1d790ebe89.xml#id-ce7a0d4d7dfa4c5aaf99fd1d790ebe89"/>
  </children>
  <children
      xsi:type="archimate:DiagramModelArchimateObject"
      id="id-cb97c4a082594fd5a4b12a5a3e15954d">
    <bounds
        x="336"
        y="192"
        width="217"
        height="85"/>
    <archimateElement
        xsi:type="archimate:Stakeholder"
        href="Stakeholder_id-eec1e1f1da4a45c5ac6c2e311c57efb9.xml#id-eec1e1f1da4a45c5ac6c2e311c57efb9"/>
  </children>
  <children
      xsi:type="archimate:DiagramModelArchimateObject"
      id="id-09cae38f14fa4f4c942d32d0d06eee6b">
    <bounds
        x="624"
        y="192"
        width="181"
        height="85"/>
    <archimateElement
        xsi:type="archimate:Stakeholder"
        href="Stakeholder_id-822a6c43041b4d70a1137c0dcc431afd.xml#id-822a6c43041b4d70a1137c0dcc431afd"/>
  </children>
  <children
      xsi:type="archimate:DiagramModelArchimateObject"
      id="id-f50dc5c588d541bb93eb16696200830d">
    <bounds
        x="84"
        y="336"
        width="145"
        height="73"/>
    <archimateElement
        xsi:type="archimate:Driver"
        href="Driver_id-54958904ef2446a8ab400c58c675b6d5.xml#id-54958904ef2446a8ab400c58c675b6d5"/>
  </children>
  <children
      xsi:type="archimate:DiagramModelArchimateObject"
      id="id-90350875e5284a16b4940fcd57b7419d">
    <bounds
        x="288"
        y="336"
        width="133"
        height="73"/>
    <archimateElement
        xsi:type="archimate:Driver"
        href="Driver_id-e38ae5714a914ae0b94af0519a911d7c.xml#id-e38ae5714a914ae0b94af0519a911d7c"/>
  </children>
  <children
      xsi:type="archimate:DiagramModelArchimateObject"
      id="id-e70bddf22022422ab5aa7d81110c4108">
    <bounds
        x="468"
        y="336"
        width="145"
        height="73"/>
    <archimateElement
        xsi:type="archimate:Driver"
        href="Driver_id-d6fc7271678647618eec6dff9047e7c1.xml#id-d6fc7271678647618eec6dff9047e7c1"/>
  </children>
  <children
      xsi:type="archimate:DiagramModelArchimateObject"
      id="id-f05ef47d205b431ebf7d4453b8e032b8">
    <bounds
        x="648"
        y="336"
        width="133"
        height="73"/>
    <archimateElement
        xsi:type="archimate:Driver"
        href="Driver_id-d08457ed8dda4af6abdf57f707ee7049.xml#id-d08457ed8dda4af6abdf57f707ee7049"/>
  </children>
  <children
      xsi:type="archimate:DiagramModelArchimateObject"
      id="id-75c6872c12bd4b3898ee42283eeeb6a3">
    <bounds
        x="84"
        y="456"
        width="145"
        height="73"/>
    <archimateElement
        xsi:type="archimate:Goal"
        href="Goal_id-422bc71c47774d8587c570cf14d02960.xml#id-422bc71c47774d8587c570cf14d02960"/>
  </children>
  <children
      xsi:type="archimate:DiagramModelArchimateObject"
      id="id-3af5ff43e8224cb09aa9048f8c932e83">
    <bounds
        x="84"
        y="564"
        width="145"
        height="73"/>
    <archimateElement
        xsi:type="archimate:Goal"
        href="Goal_id-9f0afaef9c244122980b6417e07ec5e1.xml#id-9f0afaef9c244122980b6417e07ec5e1"/>
  </children>
  <children
      xsi:type="archimate:DiagramModelArchimateObject"
      id="id-be1d4262c3af401bac805d48f3b26760">
    <bounds
        x="282"
        y="456"
        width="145"
        height="73"/>
    <archimateElement
        xsi:type="archimate:Goal"
        href="Goal_id-5f7c7ce52a72495abf879f2bd8067f2a.xml#id-5f7c7ce52a72495abf879f2bd8067f2a"/>
  </children>
  <children
      xsi:type="archimate:DiagramModelArchimateObject"
      id="id-bb4aa45d4d4741cca93b186ed35c84ea">
    <bounds
        x="282"
        y="564"
        width="145"
        height="73"/>
    <archimateElement
        xsi:type="archimate:Goal"
        href="Goal_id-4de4b251a00c425f99ab01cdb543ea80.xml#id-4de4b251a00c425f99ab01cdb543ea80"/>
  </children>
  <children
      xsi:type="archimate:DiagramModelArchimateObject"
      id="id-5d7a973a1bc249cf8a8d679911412679">
    <bounds
        x="468"
        y="456"
        width="145"
        height="73"/>
    <archimateElement
        xsi:type="archimate:Goal"
        href="Goal_id-060479419f37473cb23c6f0ea49815ad.xml#id-060479419f37473cb23c6f0ea49815ad"/>
  </children>
  <children
      xsi:type="archimate:DiagramModelArchimateObject"
      id="id-6c6ebd3cf548474c97db18af45b97b6d">
    <bounds
        x="468"
        y="564"
        width="145"
        height="73"/>
    <archimateElement
        xsi:type="archimate:Goal"
        href="Goal_id-15488314b76a44e89989671a4e725150.xml#id-15488314b76a44e89989671a4e725150"/>
  </children>
  <children
      xsi:type="archimate:DiagramModelArchimateObject"
      id="id-a250191b832946c6a0a7f6b324aff381">
    <bounds
        x="648"
        y="456"
        width="145"
        height="73"/>
    <archimateElement
        xsi:type="archimate:Goal"
        href="Goal_id-e3c9876d74e4489aba861986a6b31736.xml#id-e3c9876d74e4489aba861986a6b31736"/>
  </children>
  <children
      xsi:type="archimate:DiagramModelArchimateObject"
      id="id-d2ff498ca61b474e80945b512383edb1">
    <bounds
        x="648"
        y="564"
        width="145"
        height="73"/>
    <archimateElement
        xsi:type="archimate:Goal"
        href="Goal_id-80cebbc446604b4da6ba1945306ae3c0.xml#id-80cebbc446604b4da6ba1945306ae3c0"/>
  </children>
</archimate:ArchimateDiagramModel>
